fastapi_metrics/__init__.py
fastapi_metrics/alerting.py
fastapi_metrics/cli.py
fastapi_metrics/cli_query.py
fastapi_metrics/core.py
fastapi_metrics/middleware.py
fastapi_metrics/collectors/__init__.py
fastapi_metrics/collectors/llm_costs.py
fastapi_metrics/collectors/system.py
fastapi_metrics/exporters/__init__.py
fastapi_metrics/exporters/prometheus.py
fastapi_metrics/health/__init__.py
fastapi_metrics/health/checks.py
fastapi_metrics/health/endpoints.py
fastapi_metrics/storage/__init__.py
fastapi_metrics/storage/base.py
fastapi_metrics/storage/custom.py
fastapi_metrics/storage/memory.py
fastapi_metrics/storage/redis.py
fastapi_metrics/storage/sqlite.py
fastapi_metrics-0.3.11.dist-info/licenses/LICENSE
fastapi_metrics-0.3.11.dist-info/METADATA
fastapi_metrics-0.3.11.dist-info/WHEEL
fastapi_metrics-0.3.11.dist-info/entry_points.txt
fastapi_metrics-0.3.11.dist-info/top_level.txt
fastapi_metrics-0.3.11.dist-info/RECORD
