Metadata-Version: 2.4
Name: fastapi-metrics
Version: 0.3.11
Summary: Zero-config metrics for FastAPI apps - perfect for solo devs and MVPs
Author-email: Arpit <arpit.thukral@gmail.com>
License: MIT
Project-URL: Homepage, https://github.com/arpit0515/fastapi-metrics
Project-URL: Repository, https://github.com/arpit0515/fastapi-metrics
Project-URL: Issues, https://github.com/arpit0515/fastapi-metrics/issues
Keywords: fastapi,metrics,observability,sqlite,monitoring,redis,prometheus,kubernetes
Classifier: Development Status :: 3 - Alpha
Classifier: Intended Audience :: Developers
Classifier: License :: OSI Approved :: MIT License
Classifier: Programming Language :: Python :: 3
Classifier: Programming Language :: Python :: 3.8
Classifier: Programming Language :: Python :: 3.9
Classifier: Programming Language :: Python :: 3.10
Classifier: Programming Language :: Python :: 3.11
Classifier: Framework :: FastAPI
Requires-Python: >=3.8
License-File: LICENSE
Requires-Dist: aioboto3>=11.0.0
Requires-Dist: asyncpg>=0.27.0
Requires-Dist: rich>=13.0.0
Requires-Dist: uvicorn>=0.22.0
Requires-Dist: fastapi>=0.100.0
Requires-Dist: pydantic>=2.0.0
Requires-Dist: aiosqlite>=0.19.0
Requires-Dist: psutil>=5.9.0
Provides-Extra: dev
Requires-Dist: aioboto3>=11.0.0; extra == "dev"
Requires-Dist: asyncpg>=0.27.0; extra == "dev"
Requires-Dist: rich>=13.0.0; extra == "dev"
Requires-Dist: uvicorn>=0.22.0; extra == "dev"
Requires-Dist: pytest>=7.4.0; extra == "dev"
Requires-Dist: pytest-asyncio>=0.21.0; extra == "dev"
Requires-Dist: httpx>=0.24.0; extra == "dev"
Requires-Dist: black>=23.0.0; extra == "dev"
Requires-Dist: ruff>=0.0.280; extra == "dev"
Dynamic: license-file
